Metadata-Version: 2.1
Name: melan
Version: 0.2.0
Summary: Melan — The meta-language with Python backend.
Home-page: https://github.com/jhadida/melan
Author: Jonathan Hadida
Author-email: jonathan.hadida@unknown.invalid
License: UNKNOWN
Platform: UNKNOWN
Classifier: Development Status :: 3 - Alpha
Classifier: Intended Audience :: End Users/Desktop
Classifier: Programming Language :: Python :: 3
Classifier: Topic :: Text Processing
Classifier: License :: OSI Approved :: European Union Public Licence 1.2 (EUPL 1.2)
Classifier: Operating System :: OS Independent
Requires-Python: >=3.6
Requires-Dist: nxp
